impersonator/__init__.py
impersonator/client.py
impersonator-0.1.0.dist-info/METADATA
impersonator-0.1.0.dist-info/RECORD
impersonator-0.1.0.dist-info/WHEEL
impersonator-0.1.0.dist-info/top_level.txt
