Metadata-Version: 2.1
Name: impersonator
Version: 0.1.0
Summary: A Python client for the Impersonator service
Home-page: https://github.com/Stavatech/Impersonator-Python-Client
Author: David Brown
Author-email: davidbrownza@outlook.com
License: GPLv3
Platform: UNKNOWN
Requires-Dist: requests
Requires-Dist: mock
